terminalbars/__init__.py
terminalbars/terminalbars.py
terminalbars-2.6.5.dist-info/METADATA
terminalbars-2.6.5.dist-info/WHEEL
terminalbars-2.6.5.dist-info/top_level.txt
terminalbars-2.6.5.dist-info/RECORD
