Metadata-Version: 2.4
Name: terminalbars
Version: 2.6.5
Summary: Biblioteka w pythonie która służy do robienia czegoś podobnego do tqdm ale owiele łatwiej.
Home-page: https://github.com/superbest14/terminal-pro-bar
Author: Alexander
Author-email: alesiosawicki@gmail.com
Classifier: Programming Language :: Python :: 3
Classifier: License :: OSI Approved :: MIT License
Classifier: Operating System :: OS Independent
Requires-Python: >=3.7
